LICENSE
MANIFEST.in
README
README.md
httpd.uploader.conf
manage-stfc-stratum-uploader.py
setup.py
archer/__init__.py
archer/__init__.pyc
archer/urls.py
archer/urls.pyc
archer/wsgi.py
archer/wsgi.pyc
archer/appsetup/__init__.py
archer/appsetup/__init__.pyc
archer/appsetup/forms.py
archer/appsetup/forms.pyc
archer/appsetup/tests.py
archer/appsetup/tests.pyc
archer/appsetup/urls.py
archer/appsetup/urls.pyc
archer/appsetup/views.py
archer/appsetup/views.pyc
archer/appsetup/templates/appsetup/admin.html
archer/appsetup/templates/appsetup/filesystems.html
archer/appsetup/templates/appsetup/index.html
archer/assets/coffee/projects/tree.coffee
archer/assets/css/.gitkeep
archer/assets/js/core/ajax.js
archer/assets/js/core/jquery-2.0.3.js
archer/assets/js/core/jquery-2.0.3.min.map
archer/assets/sass/core/custom_bootstrap.sass
archer/assets/sass/projects/actions.sass
archer/assets/sass/projects/tree.sass
archer/core/__init__.py
archer/core/__init__.pyc
archer/core/decorators.py
archer/core/decorators.pyc
archer/core/exceptions.py
archer/core/exceptions.pyc
archer/core/middleware.py
archer/core/middleware.pyc
archer/core/templates/403.html
archer/core/templates/404.html
archer/core/templates/_filelist.html
archer/core/templates/base.html
archer/core/templates/debug.html
archer/core/templates/nav.html
archer/core/templates/unauthenticated.html
archer/custom_auth/__init__.py
archer/custom_auth/__init__.pyc
archer/custom_auth/admin.py
archer/custom_auth/admin.pyc
archer/custom_auth/models.py
archer/custom_auth/models.pyc
archer/custom_auth/management/__init__.py
archer/custom_auth/management/__init__.pyc
archer/custom_auth/management/commands/__init__.py
archer/custom_auth/management/commands/__init__.pyc
archer/custom_auth/management/commands/sync_perms.py
archer/custom_auth/management/commands/sync_perms.pyc
archer/custom_auth/migrations/0001_initial.py
archer/custom_auth/migrations/0001_initial.pyc
archer/custom_auth/migrations/__init__.py
stfc_stratum_uploader.egg-info/PKG-INFO
stfc_stratum_uploader.egg-info/SOURCES.txt
stfc_stratum_uploader.egg-info/dependency_links.txt
stfc_stratum_uploader.egg-info/not-zip-safe
stfc_stratum_uploader.egg-info/requires.txt
stfc_stratum_uploader.egg-info/top_level.txt