Metadata-Version: 1.0
Name: stfc-stratum-uploader
Version: 0.1.4
Summary: Provides interface for uploading and distributing software through cvmfs repositories.
Home-page: git://github.com/mknapik/uploader.git
Author: Michal Knapik
Author-email: Michael.Knapik@stfc.ac.uk
License: Apache License
Keywords: cvmfs,django,uploader,vo,cern,stfc,ral
Platform: UNKNOWN
